awsipenum/__init__.py
awsipenum/cli.py
awsipenum/cloudfront.py
awsipenum/ec2.py
awsipenum/elb.py
awsipenum/elbv2.py
awsipenum/msg.py
awsipenum/rds.py
awsipenum/render.py
awsipenum/sts.py
awsipenum-0.1.11.dist-info/LICENSE
awsipenum-0.1.11.dist-info/METADATA
awsipenum-0.1.11.dist-info/WHEEL
awsipenum-0.1.11.dist-info/entry_points.txt
awsipenum-0.1.11.dist-info/top_level.txt
awsipenum-0.1.11.dist-info/RECORD
