Metadata-Version: 2.1
Name: awsipenum
Version: 0.1.11
Summary: List your AWS IPs
Home-page: https://github.com/momelod/awsipenum
Author: Steve Melo
Author-email: Steve Melo <momelod@gmail.com>
Project-URL: Repository, https://github.com/momelod/awsipenum
Classifier: Programming Language :: Python :: 3
Classifier: License :: OSI Approved :: MIT License
Classifier: Operating System :: OS Independent
Requires-Python: >=3.6
License-File: LICENSE
Requires-Dist: boto3
Requires-Dist: botocore
Requires-Dist: ipaddress
Requires-Dist: requests
Requires-Dist: pyaml
